README.txt
setup.py
Bugzilla_ETL.egg-info/PKG-INFO
Bugzilla_ETL.egg-info/SOURCES.txt
Bugzilla_ETL.egg-info/dependency_links.txt
Bugzilla_ETL.egg-info/entry_points.txt
Bugzilla_ETL.egg-info/not-zip-safe
Bugzilla_ETL.egg-info/requires.txt
Bugzilla_ETL.egg-info/top_level.txt
bzETL/__init__.py
bzETL/alias_analysis.py
bzETL/bz_etl.py
bzETL/extract_bugzilla.py
bzETL/parse_bug_history.py
bzETL/replicate.py
bzETL/transform_bugzilla.py
bzETL/util/__init__.py
bzETL/util/cnv.py
bzETL/util/db.py
bzETL/util/elasticsearch.py
bzETL/util/emailer.py
bzETL/util/files.py
bzETL/util/jsons.py
bzETL/util/logs.py
bzETL/util/maths.py
bzETL/util/multiprocess.py
bzETL/util/multiset.py
bzETL/util/multithread.py
bzETL/util/randoms.py
bzETL/util/sql.py
bzETL/util/startup.py
bzETL/util/stats.py
bzETL/util/strings.py
bzETL/util/struct.py
bzETL/util/threads.py
bzETL/util/timer.py
bzETL/util/queries/Q.py
bzETL/util/queries/__init__.py
bzETL/util/queries/windows.py
resources/json/bug_comments.json
resources/json/bug_version.json
resources/json/bugzilla_aliases.json
resources/scripts/alias_analysis.bat
resources/scripts/bz_etl.bat
resources/scripts/fileload.bat
resources/scripts/replicate.bat
resources/settings/bz_etl_settings_example.json
resources/settings/fileload_settings_example.json
resources/settings/replication_settings_example.json
resources/settings/test_settings_example.json