Metadata-Version: 1.1
Name: Bugzilla-ETL
Version: 0.3.13326
Summary: Mozilla Bugzilla Bug Version ETL
Home-page: https://github.com/klahnakoski/Bugzilla-ETL
Author: Kyle Lahnakoski
Author-email: kyle@lahnakoski.com
License: MPL 2.0
Platform: UNKNOWN
Classifier: Development Status :: 4 - Beta
Classifier: Topic :: Utilities
Classifier: License :: OSI Approved :: Mozilla Public License 2.0 (MPL 2.0)
